[
  {
    "abstract": {
      "description": "The ATLAS Collaboration has released 10/fb of collision data at a centre-of-mass energy of 13 TeV from the 2016 data-taking period, intended solely for educational purposes, to the general public.\n This set of real data is accompanied by matching simulated samples of Standard Model processes and a selection of Beyond the Standard Model signals."
    },
    "accelerator": "CERN-LHC",
    "collaboration": {
      "name": "ATLAS Collaboration"
    },
    "collections": [
      "ATLAS-Derived-Datasets"
    ],
    "collision_information": {
      "energy": "13TeV",
      "type": "pp"
    },
    "date_created": [
      "2016"
    ],
    "date_published": "2020",
    "distribution": {
      "formats": [
        "root",
        "zip"
      ],
      "number_files": 111,
      "size": 975705245
    },
    "doi": "10.7483/OPENDATA.ATLAS.2Y1T.TLGL",
    "experiment": [
      "ATLAS"
    ],
    "files": [
      {
        "checksum": "adler32:b934c380",
        "size": 446971392,
        "uri": "root://eospublic.cern.ch//eos/opendata/atlas/OutreachDatasets/2020-08-19/4lep.zip"
      },
      {
        "checksum": "adler32:b6a8df64",
        "size": 33765,
        "uri": "root://eospublic.cern.ch//eos/opendata/atlas/OutreachDatasets/2020-08-19/4lep/Data/data_A.4lep.root"
      },
      {
        "checksum": "adler32:f870fe84",
        "size": 68738,
        "uri": "root://eospublic.cern.ch//eos/opendata/atlas/OutreachDatasets/2020-08-19/4lep/Data/data_B.4lep.root"
      },
      {
        "checksum": "adler32:c7681404",
        "size": 92295,
        "uri": "root://eospublic.cern.ch//eos/opendata/atlas/OutreachDatasets/2020-08-19/4lep/Data/data_C.4lep.root"
      },
      {
        "checksum": "adler32:266a7775",
        "size": 139606,
        "uri": "root://eospublic.cern.ch//eos/opendata/atlas/OutreachDatasets/2020-08-19/4lep/Data/data_D.4lep.root"
      },
      {
        "checksum": "adler32:142a907b",
        "size": 21508,
        "uri": "root://eospublic.cern.ch//eos/opendata/atlas/OutreachDatasets/2020-08-19/4lep/MC/mc_301215.ZPrime2000_ee.4lep.root"
      },
      {
        "checksum": "adler32:e81dd0eb",
        "size": 20687,
        "uri": "root://eospublic.cern.ch//eos/opendata/atlas/OutreachDatasets/2020-08-19/4lep/MC/mc_301216.ZPrime3000_ee.4lep.root"
      },
      {
        "checksum": "adler32:2336bc75",
        "size": 46283,
        "uri": "root://eospublic.cern.ch//eos/opendata/atlas/OutreachDatasets/2020-08-19/4lep/MC/mc_301220.ZPrime2000_mumu.4lep.root"
      },
      {
        "checksum": "adler32:415ee761",
        "size": 41798,
        "uri": "root://eospublic.cern.ch//eos/opendata/atlas/OutreachDatasets/2020-08-19/4lep/MC/mc_301221.ZPrime3000_mumu.4lep.root"
      },
      {
        "checksum": "adler32:9d100851",
        "size": 21279,
        "uri": "root://eospublic.cern.ch//eos/opendata/atlas/OutreachDatasets/2020-08-19/4lep/MC/mc_301322.ZPrime400_tt.4lep.root"
      },
      {
        "checksum": "adler32:a18b0956",
        "size": 19823,
        "uri": "root://eospublic.cern.ch//eos/opendata/atlas/OutreachDatasets/2020-08-19/4lep/MC/mc_301323.ZPrime500_tt.4lep.root"
      },
      {
        "checksum": "adler32:c8557fd3",
        "size": 292662,
        "uri": "root://eospublic.cern.ch//eos/opendata/atlas/OutreachDatasets/2020-08-19/4lep/MC/mc_303329.RS_G_ZZ_llll_c10_m1000.4lep.root"
      },
      {
        "checksum": "adler32:72a1c728",
        "size": 283757,
        "uri": "root://eospublic.cern.ch//eos/opendata/atlas/OutreachDatasets/2020-08-19/4lep/MC/mc_303334.RS_G_ZZ_llll_c10_m2000.4lep.root"
      },
      {
        "checksum": "adler32:1f06035a",
        "size": 21306,
        "uri": "root://eospublic.cern.ch//eos/opendata/atlas/OutreachDatasets/2020-08-19/4lep/MC/mc_305553.Gee_01_1000.4lep.root"
      },
      {
        "checksum": "adler32:3abaab7d",
        "size": 20631,
        "uri": "root://eospublic.cern.ch//eos/opendata/atlas/OutreachDatasets/2020-08-19/4lep/MC/mc_305556.Gee_01_2000.4lep.root"
      },
      {
        "checksum": "adler32:afa35ca4",
        "size": 21206,
        "uri": "root://eospublic.cern.ch//eos/opendata/atlas/OutreachDatasets/2020-08-19/4lep/MC/mc_305559.Gee_01_3000.4lep.root"
      },
      {
        "checksum": "adler32:280ee091",
        "size": 21180,
        "uri": "root://eospublic.cern.ch//eos/opendata/atlas/OutreachDatasets/2020-08-19/4lep/MC/mc_305562.Gee_01_4000.4lep.root"
      },
      {
        "checksum": "adler32:9fa4a006",
        "size": 21341,
        "uri": "root://eospublic.cern.ch//eos/opendata/atlas/OutreachDatasets/2020-08-19/4lep/MC/mc_305571.Gmumu_01_1000.4lep.root"
      },
      {
        "checksum": "adler32:0361d676",
        "size": 21371,
        "uri": "root://eospublic.cern.ch//eos/opendata/atlas/OutreachDatasets/2020-08-19/4lep/MC/mc_305574.Gmumu_01_2000.4lep.root"
      },
      {
        "checksum": "adler32:99205beb",
        "size": 19906,
        "uri": "root://eospublic.cern.ch//eos/opendata/atlas/OutreachDatasets/2020-08-19/4lep/MC/mc_305577.Gmumu_01_3000.4lep.root"
      },
      {
        "checksum": "adler32:692a8c3a",
        "size": 19895,
        "uri": "root://eospublic.cern.ch//eos/opendata/atlas/OutreachDatasets/2020-08-19/4lep/MC/mc_305580.Gmumu_01_4000.4lep.root"
      },
      {
        "checksum": "adler32:6859a25f",
        "size": 1451404,
        "uri": "root://eospublic.cern.ch//eos/opendata/atlas/OutreachDatasets/2020-08-19/4lep/MC/mc_307431.RS_G_ZZ_llll_c10_m0200.4lep.root"
      },
      {
        "checksum": "adler32:70633804",
        "size": 2213278,
        "uri": "root://eospublic.cern.ch//eos/opendata/atlas/OutreachDatasets/2020-08-19/4lep/MC/mc_307434.RS_G_ZZ_llll_c10_m0500.4lep.root"
      },
      {
        "checksum": "adler32:2a130322",
        "size": 2754772,
        "uri": "root://eospublic.cern.ch//eos/opendata/atlas/OutreachDatasets/2020-08-19/4lep/MC/mc_307439.RS_G_ZZ_llll_c10_m1500.4lep.root"
      },
      {
        "checksum": "adler32:43b610d8",
        "size": 22749,
        "uri": "root://eospublic.cern.ch//eos/opendata/atlas/OutreachDatasets/2020-08-19/4lep/MC/mc_341122.ggH125_tautaull.4lep.root"
      },
      {
        "checksum": "adler32:2c629095",
        "size": 28894,
        "uri": "root://eospublic.cern.ch//eos/opendata/atlas/OutreachDatasets/2020-08-19/4lep/MC/mc_341155.VBFH125_tautaull.4lep.root"
      },
      {
        "checksum": "adler32:18c94313",
        "size": 5293850,
        "uri": "root://eospublic.cern.ch//eos/opendata/atlas/OutreachDatasets/2020-08-19/4lep/MC/mc_341947.ZH125_ZZ4lep.4lep.root"
      },
      {
        "checksum": "adler32:a923e2e8",
        "size": 5528294,
        "uri": "root://eospublic.cern.ch//eos/opendata/atlas/OutreachDatasets/2020-08-19/4lep/MC/mc_341964.WH125_ZZ4lep.4lep.root"
      },
      {
        "checksum": "adler32:e551abab",
        "size": 60503237,
        "uri": "root://eospublic.cern.ch//eos/opendata/atlas/OutreachDatasets/2020-08-19/4lep/MC/mc_344235.VBFH125_ZZ4lep.4lep.root"
      },
      {
        "checksum": "adler32:1ea0e560",
        "size": 50518236,
        "uri": "root://eospublic.cern.ch//eos/opendata/atlas/OutreachDatasets/2020-08-19/4lep/MC/mc_345060.ggH125_ZZ4lep.4lep.root"
      },
      {
        "checksum": "adler32:33edbc1e",
        "size": 26850,
        "uri": "root://eospublic.cern.ch//eos/opendata/atlas/OutreachDatasets/2020-08-19/4lep/MC/mc_345323.VBFH125_WW2lep.4lep.root"
      },
      {
        "checksum": "adler32:9699d850",
        "size": 29899,
        "uri": "root://eospublic.cern.ch//eos/opendata/atlas/OutreachDatasets/2020-08-19/4lep/MC/mc_345324.ggH125_WW2lep.4lep.root"
      },
      {
        "checksum": "adler32:be5c8a49",
        "size": 46457,
        "uri": "root://eospublic.cern.ch//eos/opendata/atlas/OutreachDatasets/2020-08-19/4lep/MC/mc_345325.WpH125J_qqWW2lep.4lep.root"
      },
      {
        "checksum": "adler32:877fa565",
        "size": 51697,
        "uri": "root://eospublic.cern.ch//eos/opendata/atlas/OutreachDatasets/2020-08-19/4lep/MC/mc_345327.WpH125J_lvWW2lep.4lep.root"
      },
      {
        "checksum": "adler32:ca016954",
        "size": 787504,
        "uri": "root://eospublic.cern.ch//eos/opendata/atlas/OutreachDatasets/2020-08-19/4lep/MC/mc_345336.ZH125J_qqWW2lep.4lep.root"
      },
      {
        "checksum": "adler32:549dfdd1",
        "size": 11167200,
        "uri": "root://eospublic.cern.ch//eos/opendata/atlas/OutreachDatasets/2020-08-19/4lep/MC/mc_345337.ZH125J_llWW2lep.4lep.root"
      },
      {
        "checksum": "adler32:1bc41e1e",
        "size": 22679,
        "uri": "root://eospublic.cern.ch//eos/opendata/atlas/OutreachDatasets/2020-08-19/4lep/MC/mc_345445.ZH125J_vvWW2lep.4lep.root"
      },
      {
        "checksum": "adler32:f38878a3",
        "size": 9645,
        "uri": "root://eospublic.cern.ch//eos/opendata/atlas/OutreachDatasets/2020-08-19/4lep/MC/mc_361100.Wplusenu.4lep.root"
      },
      {
        "checksum": "adler32:4f3e3203",
        "size": 9659,
        "uri": "root://eospublic.cern.ch//eos/opendata/atlas/OutreachDatasets/2020-08-19/4lep/MC/mc_361101.Wplusmunu.4lep.root"
      },
      {
        "checksum": "adler32:9e455a8b",
        "size": 9650,
        "uri": "root://eospublic.cern.ch//eos/opendata/atlas/OutreachDatasets/2020-08-19/4lep/MC/mc_361102.Wplustaunu.4lep.root"
      },
      {
        "checksum": "adler32:03837a6e",
        "size": 9612,
        "uri": "root://eospublic.cern.ch//eos/opendata/atlas/OutreachDatasets/2020-08-19/4lep/MC/mc_361103.Wminusenu.4lep.root"
      },
      {
        "checksum": "adler32:602f56ae",
        "size": 9667,
        "uri": "root://eospublic.cern.ch//eos/opendata/atlas/OutreachDatasets/2020-08-19/4lep/MC/mc_361104.Wminusmunu.4lep.root"
      },
      {
        "checksum": "adler32:9a8a66c3",
        "size": 9653,
        "uri": "root://eospublic.cern.ch//eos/opendata/atlas/OutreachDatasets/2020-08-19/4lep/MC/mc_361105.Wminustaunu.4lep.root"
      },
      {
        "checksum": "adler32:d58a256c",
        "size": 299577,
        "uri": "root://eospublic.cern.ch//eos/opendata/atlas/OutreachDatasets/2020-08-19/4lep/MC/mc_361106.Zee.4lep.root"
      },
      {
        "checksum": "adler32:8f471536",
        "size": 233914,
        "uri": "root://eospublic.cern.ch//eos/opendata/atlas/OutreachDatasets/2020-08-19/4lep/MC/mc_361107.Zmumu.4lep.root"
      },
      {
        "checksum": "adler32:633cc8b3",
        "size": 23858,
        "uri": "root://eospublic.cern.ch//eos/opendata/atlas/OutreachDatasets/2020-08-19/4lep/MC/mc_361108.Ztautau.4lep.root"
      },
      {
        "checksum": "adler32:823275b1",
        "size": 111159,
        "uri": "root://eospublic.cern.ch//eos/opendata/atlas/OutreachDatasets/2020-08-19/4lep/MC/mc_363356.ZqqZll.4lep.root"
      },
      {
        "checksum": "adler32:2d439fbe",
        "size": 45233,
        "uri": "root://eospublic.cern.ch//eos/opendata/atlas/OutreachDatasets/2020-08-19/4lep/MC/mc_363358.WqqZll.4lep.root"
      },
      {
        "checksum": "adler32:2e875c51",
        "size": 9590,
        "uri": "root://eospublic.cern.ch//eos/opendata/atlas/OutreachDatasets/2020-08-19/4lep/MC/mc_363359.WpqqWmlv.4lep.root"
      },
      {
        "checksum": "adler32:97d08aea",
        "size": 9696,
        "uri": "root://eospublic.cern.ch//eos/opendata/atlas/OutreachDatasets/2020-08-19/4lep/MC/mc_363360.WplvWmqq.4lep.root"
      },
      {
        "checksum": "adler32:f7d042bb",
        "size": 9616,
        "uri": "root://eospublic.cern.ch//eos/opendata/atlas/OutreachDatasets/2020-08-19/4lep/MC/mc_363489.WlvZqq.4lep.root"
      },
      {
        "checksum": "adler32:6298e6cb",
        "size": 179082866,
        "uri": "root://eospublic.cern.ch//eos/opendata/atlas/OutreachDatasets/2020-08-19/4lep/MC/mc_363490.llll.4lep.root"
      },
      {
        "checksum": "adler32:a7c04986",
        "size": 3304821,
        "uri": "root://eospublic.cern.ch//eos/opendata/atlas/OutreachDatasets/2020-08-19/4lep/MC/mc_363491.lllv.4lep.root"
      },
      {
        "checksum": "adler32:fd1cedd3",
        "size": 74111,
        "uri": "root://eospublic.cern.ch//eos/opendata/atlas/OutreachDatasets/2020-08-19/4lep/MC/mc_363492.llvv.4lep.root"
      },
      {
        "checksum": "adler32:2b0c5969",
        "size": 9574,
        "uri": "root://eospublic.cern.ch//eos/opendata/atlas/OutreachDatasets/2020-08-19/4lep/MC/mc_363493.lvvv.4lep.root"
      },
      {
        "checksum": "adler32:4cc3c06a",
        "size": 34477,
        "uri": "root://eospublic.cern.ch//eos/opendata/atlas/OutreachDatasets/2020-08-19/4lep/MC/mc_364100.Zmumu_PTV0_70_CVetoBVeto.4lep.root"
      },
      {
        "checksum": "adler32:5065689d",
        "size": 39536,
        "uri": "root://eospublic.cern.ch//eos/opendata/atlas/OutreachDatasets/2020-08-19/4lep/MC/mc_364101.Zmumu_PTV0_70_CFilterBVeto.4lep.root"
      },
      {
        "checksum": "adler32:3e5fbc9c",
        "size": 122860,
        "uri": "root://eospublic.cern.ch//eos/opendata/atlas/OutreachDatasets/2020-08-19/4lep/MC/mc_364102.Zmumu_PTV0_70_BFilter.4lep.root"
      },
      {
        "checksum": "adler32:bbec4064",
        "size": 36930,
        "uri": "root://eospublic.cern.ch//eos/opendata/atlas/OutreachDatasets/2020-08-19/4lep/MC/mc_364103.Zmumu_PTV70_140_CVetoBVeto.4lep.root"
      },
      {
        "checksum": "adler32:c3e5d6ff",
        "size": 29885,
        "uri": "root://eospublic.cern.ch//eos/opendata/atlas/OutreachDatasets/2020-08-19/4lep/MC/mc_364104.Zmumu_PTV70_140_CFilterBVeto.4lep.root"
      },
      {
        "checksum": "adler32:42cbd056",
        "size": 155054,
        "uri": "root://eospublic.cern.ch//eos/opendata/atlas/OutreachDatasets/2020-08-19/4lep/MC/mc_364105.Zmumu_PTV70_140_BFilter.4lep.root"
      },
      {
        "checksum": "adler32:c935c4f4",
        "size": 40174,
        "uri": "root://eospublic.cern.ch//eos/opendata/atlas/OutreachDatasets/2020-08-19/4lep/MC/mc_364106.Zmumu_PTV140_280_CVetoBVeto.4lep.root"
      },
      {
        "checksum": "adler32:7848ba1e",
        "size": 30809,
        "uri": "root://eospublic.cern.ch//eos/opendata/atlas/OutreachDatasets/2020-08-19/4lep/MC/mc_364107.Zmumu_PTV140_280_CFilterBVeto.4lep.root"
      },
      {
        "checksum": "adler32:38ab72da",
        "size": 292029,
        "uri": "root://eospublic.cern.ch//eos/opendata/atlas/OutreachDatasets/2020-08-19/4lep/MC/mc_364108.Zmumu_PTV140_280_BFilter.4lep.root"
      },
      {
        "checksum": "adler32:6e684e2f",
        "size": 27688,
        "uri": "root://eospublic.cern.ch//eos/opendata/atlas/OutreachDatasets/2020-08-19/4lep/MC/mc_364109.Zmumu_PTV280_500_CVetoBVeto.4lep.root"
      },
      {
        "checksum": "adler32:a53346d8",
        "size": 27023,
        "uri": "root://eospublic.cern.ch//eos/opendata/atlas/OutreachDatasets/2020-08-19/4lep/MC/mc_364110.Zmumu_PTV280_500_CFilterBVeto.4lep.root"
      },
      {
        "checksum": "adler32:d6b837f0",
        "size": 67867,
        "uri": "root://eospublic.cern.ch//eos/opendata/atlas/OutreachDatasets/2020-08-19/4lep/MC/mc_364111.Zmumu_PTV280_500_BFilter.4lep.root"
      },
      {
        "checksum": "adler32:f6aaa1d9",
        "size": 50368,
        "uri": "root://eospublic.cern.ch//eos/opendata/atlas/OutreachDatasets/2020-08-19/4lep/MC/mc_364112.Zmumu_PTV500_1000.4lep.root"
      },
      {
        "checksum": "adler32:46a92fcc",
        "size": 31030,
        "uri": "root://eospublic.cern.ch//eos/opendata/atlas/OutreachDatasets/2020-08-19/4lep/MC/mc_364113.Zmumu_PTV1000_E_CMS.4lep.root"
      },
      {
        "checksum": "adler32:2cc7d122",
        "size": 43132,
        "uri": "root://eospublic.cern.ch//eos/opendata/atlas/OutreachDatasets/2020-08-19/4lep/MC/mc_364114.Zee_PTV0_70_CVetoBVeto.4lep.root"
      },
      {
        "checksum": "adler32:687864e0",
        "size": 47524,
        "uri": "root://eospublic.cern.ch//eos/opendata/atlas/OutreachDatasets/2020-08-19/4lep/MC/mc_364115.Zee_PTV0_70_CFilterBVeto.4lep.root"
      },
      {
        "checksum": "adler32:90f3ddd4",
        "size": 185041,
        "uri": "root://eospublic.cern.ch//eos/opendata/atlas/OutreachDatasets/2020-08-19/4lep/MC/mc_364116.Zee_PTV0_70_BFilter.4lep.root"
      },
      {
        "checksum": "adler32:80ceeb8b",
        "size": 43563,
        "uri": "root://eospublic.cern.ch//eos/opendata/atlas/OutreachDatasets/2020-08-19/4lep/MC/mc_364117.Zee_PTV70_140_CVetoBVeto.4lep.root"
      },
      {
        "checksum": "adler32:69400337",
        "size": 38119,
        "uri": "root://eospublic.cern.ch//eos/opendata/atlas/OutreachDatasets/2020-08-19/4lep/MC/mc_364118.Zee_PTV70_140_CFilterBVeto.4lep.root"
      },
      {
        "checksum": "adler32:2add7f08",
        "size": 288878,
        "uri": "root://eospublic.cern.ch//eos/opendata/atlas/OutreachDatasets/2020-08-19/4lep/MC/mc_364119.Zee_PTV70_140_BFilter.4lep.root"
      },
      {
        "checksum": "adler32:1bf5b184",
        "size": 47543,
        "uri": "root://eospublic.cern.ch//eos/opendata/atlas/OutreachDatasets/2020-08-19/4lep/MC/mc_364120.Zee_PTV140_280_CVetoBVeto.4lep.root"
      },
      {
        "checksum": "adler32:ee4c9f95",
        "size": 42961,
        "uri": "root://eospublic.cern.ch//eos/opendata/atlas/OutreachDatasets/2020-08-19/4lep/MC/mc_364121.Zee_PTV140_280_CFilterBVeto.4lep.root"
      },
      {
        "checksum": "adler32:1934abe3",
        "size": 543329,
        "uri": "root://eospublic.cern.ch//eos/opendata/atlas/OutreachDatasets/2020-08-19/4lep/MC/mc_364122.Zee_PTV140_280_BFilter.4lep.root"
      },
      {
        "checksum": "adler32:453c601a",
        "size": 34910,
        "uri": "root://eospublic.cern.ch//eos/opendata/atlas/OutreachDatasets/2020-08-19/4lep/MC/mc_364123.Zee_PTV280_500_CVetoBVeto.4lep.root"
      },
      {
        "checksum": "adler32:c5b1618e",
        "size": 29578,
        "uri": "root://eospublic.cern.ch//eos/opendata/atlas/OutreachDatasets/2020-08-19/4lep/MC/mc_364124.Zee_PTV280_500_CFilterBVeto.4lep.root"
      },
      {
        "checksum": "adler32:ce6eb7f3",
        "size": 116792,
        "uri": "root://eospublic.cern.ch//eos/opendata/atlas/OutreachDatasets/2020-08-19/4lep/MC/mc_364125.Zee_PTV280_500_BFilter.4lep.root"
      },
      {
        "checksum": "adler32:16b253a3",
        "size": 67232,
        "uri": "root://eospublic.cern.ch//eos/opendata/atlas/OutreachDatasets/2020-08-19/4lep/MC/mc_364126.Zee_PTV500_1000.4lep.root"
      },
      {
        "checksum": "adler32:41424f2b",
        "size": 37801,
        "uri": "root://eospublic.cern.ch//eos/opendata/atlas/OutreachDatasets/2020-08-19/4lep/MC/mc_364127.Zee_PTV1000_E_CMS.4lep.root"
      },
      {
        "checksum": "adler32:fbd22bd3",
        "size": 19902,
        "uri": "root://eospublic.cern.ch//eos/opendata/atlas/OutreachDatasets/2020-08-19/4lep/MC/mc_364128.Ztautau_PTV0_70_CVetoBVeto.4lep.root"
      },
      {
        "checksum": "adler32:fd19637f",
        "size": 20598,
        "uri": "root://eospublic.cern.ch//eos/opendata/atlas/OutreachDatasets/2020-08-19/4lep/MC/mc_364129.Ztautau_PTV0_70_CFilterBVeto.4lep.root"
      },
      {
        "checksum": "adler32:823afc42",
        "size": 23411,
        "uri": "root://eospublic.cern.ch//eos/opendata/atlas/OutreachDatasets/2020-08-19/4lep/MC/mc_364130.Ztautau_PTV0_70_BFilter.4lep.root"
      },
      {
        "checksum": "adler32:5775feb7",
        "size": 19864,
        "uri": "root://eospublic.cern.ch//eos/opendata/atlas/OutreachDatasets/2020-08-19/4lep/MC/mc_364131.Ztautau_PTV70_140_CVetoBVeto.4lep.root"
      },
      {
        "checksum": "adler32:dad11e61",
        "size": 19841,
        "uri": "root://eospublic.cern.ch//eos/opendata/atlas/OutreachDatasets/2020-08-19/4lep/MC/mc_364132.Ztautau_PTV70_140_CFilterBVeto.4lep.root"
      },
      {
        "checksum": "adler32:ea8393d9",
        "size": 28358,
        "uri": "root://eospublic.cern.ch//eos/opendata/atlas/OutreachDatasets/2020-08-19/4lep/MC/mc_364133.Ztautau_PTV70_140_BFilter.4lep.root"
      },
      {
        "checksum": "adler32:541fbfd3",
        "size": 21508,
        "uri": "root://eospublic.cern.ch//eos/opendata/atlas/OutreachDatasets/2020-08-19/4lep/MC/mc_364134.Ztautau_PTV140_280_CVetoBVeto.4lep.root"
      },
      {
        "checksum": "adler32:0e809699",
        "size": 20706,
        "uri": "root://eospublic.cern.ch//eos/opendata/atlas/OutreachDatasets/2020-08-19/4lep/MC/mc_364135.Ztautau_PTV140_280_CFilterBVeto.4lep.root"
      },
      {
        "checksum": "adler32:105bc556",
        "size": 25595,
        "uri": "root://eospublic.cern.ch//eos/opendata/atlas/OutreachDatasets/2020-08-19/4lep/MC/mc_364136.Ztautau_PTV140_280_BFilter.4lep.root"
      },
      {
        "checksum": "adler32:d7c545fe",
        "size": 19916,
        "uri": "root://eospublic.cern.ch//eos/opendata/atlas/OutreachDatasets/2020-08-19/4lep/MC/mc_364137.Ztautau_PTV280_500_CVetoBVeto.4lep.root"
      },
      {
        "checksum": "adler32:bc9db663",
        "size": 20042,
        "uri": "root://eospublic.cern.ch//eos/opendata/atlas/OutreachDatasets/2020-08-19/4lep/MC/mc_364138.Ztautau_PTV280_500_CFilterBVeto.4lep.root"
      },
      {
        "checksum": "adler32:09e8041b",
        "size": 25153,
        "uri": "root://eospublic.cern.ch//eos/opendata/atlas/OutreachDatasets/2020-08-19/4lep/MC/mc_364139.Ztautau_PTV280_500_BFilter.4lep.root"
      },
      {
        "checksum": "adler32:f01833d2",
        "size": 21648,
        "uri": "root://eospublic.cern.ch//eos/opendata/atlas/OutreachDatasets/2020-08-19/4lep/MC/mc_364140.Ztautau_PTV500_1000.4lep.root"
      },
      {
        "checksum": "adler32:bc3190b9",
        "size": 176035691,
        "uri": "root://eospublic.cern.ch//eos/opendata/atlas/OutreachDatasets/2020-08-19/4lep/MC/mc_364250.llll_filter.4lep.root"
      },
      {
        "checksum": "adler32:c2baeb65",
        "size": 93126,
        "uri": "root://eospublic.cern.ch//eos/opendata/atlas/OutreachDatasets/2020-08-19/4lep/MC/mc_370114.GG_ttn1_1200_5000_1.4lep.root"
      },
      {
        "checksum": "adler32:dbaf9e88",
        "size": 111850,
        "uri": "root://eospublic.cern.ch//eos/opendata/atlas/OutreachDatasets/2020-08-19/4lep/MC/mc_370118.GG_ttn1_1200_5000_600.4lep.root"
      },
      {
        "checksum": "adler32:1e37dfb8",
        "size": 78806,
        "uri": "root://eospublic.cern.ch//eos/opendata/atlas/OutreachDatasets/2020-08-19/4lep/MC/mc_370129.GG_ttn1_1400_5000_1.4lep.root"
      },
      {
        "checksum": "adler32:1e45db00",
        "size": 71760,
        "uri": "root://eospublic.cern.ch//eos/opendata/atlas/OutreachDatasets/2020-08-19/4lep/MC/mc_370144.GG_ttn1_1600_5000_1.4lep.root"
      },
      {
        "checksum": "adler32:8d8b3a96",
        "size": 391352,
        "uri": "root://eospublic.cern.ch//eos/opendata/atlas/OutreachDatasets/2020-08-19/4lep/MC/mc_410000.ttbar_lep.4lep.root"
      },
      {
        "checksum": "adler32:3f5ada65",
        "size": 20698,
        "uri": "root://eospublic.cern.ch//eos/opendata/atlas/OutreachDatasets/2020-08-19/4lep/MC/mc_410011.single_top_tchan.4lep.root"
      },
      {
        "checksum": "adler32:03b4eb71",
        "size": 20802,
        "uri": "root://eospublic.cern.ch//eos/opendata/atlas/OutreachDatasets/2020-08-19/4lep/MC/mc_410012.single_antitop_tchan.4lep.root"
      },
      {
        "checksum": "adler32:7685e876",
        "size": 43677,
        "uri": "root://eospublic.cern.ch//eos/opendata/atlas/OutreachDatasets/2020-08-19/4lep/MC/mc_410013.single_top_wtchan.4lep.root"
      },
      {
        "checksum": "adler32:ff89bae5",
        "size": 39845,
        "uri": "root://eospublic.cern.ch//eos/opendata/atlas/OutreachDatasets/2020-08-19/4lep/MC/mc_410014.single_antitop_wtchan.4lep.root"
      },
      {
        "checksum": "adler32:a613e43d",
        "size": 20778,
        "uri": "root://eospublic.cern.ch//eos/opendata/atlas/OutreachDatasets/2020-08-19/4lep/MC/mc_410025.single_top_schan.4lep.root"
      },
      {
        "checksum": "adler32:f4fd8146",
        "size": 20609,
        "uri": "root://eospublic.cern.ch//eos/opendata/atlas/OutreachDatasets/2020-08-19/4lep/MC/mc_410026.single_antitop_schan.4lep.root"
      },
      {
        "checksum": "adler32:3145248c",
        "size": 545480,
        "uri": "root://eospublic.cern.ch//eos/opendata/atlas/OutreachDatasets/2020-08-19/4lep/MC/mc_410155.ttW.4lep.root"
      },
      {
        "checksum": "adler32:83a7903b",
        "size": 12812484,
        "uri": "root://eospublic.cern.ch//eos/opendata/atlas/OutreachDatasets/2020-08-19/4lep/MC/mc_410218.ttee.4lep.root"
      },
      {
        "checksum": "adler32:0b8ff7d0",
        "size": 10620282,
        "uri": "root://eospublic.cern.ch//eos/opendata/atlas/OutreachDatasets/2020-08-19/4lep/MC/mc_410219.ttmumu.4lep.root"
      }
    ],
    "license": {
      "attribution": "CC0-1.0"
    },
    "methodology": {
      "description": "Events selected with at least four leptons (electron or muon).\n Both real data and simulated samples are subjected to a loose event preselection to reduce the processing time by reducing the overall number of events that have to be analysed.\n The preselection consists of a set of object selection criteria and a subsequent event selection acting on these preselected objects."
    },
    "publisher": "CERN Open Data Portal",
    "recid": "15005",
    "run_period": [
      "Run2016"
    ],
    "title": "ATLAS 13 TeV samples collection at least four leptons (electron or muon), for 2020 Open Data release",
    "type": {
      "primary": "Dataset",
      "secondary": [
        "Derived",
        "Simulated"
      ]
    },
    "usage": {
      "description": "<p>This dataset is provided as a zipped tarball (<code>4lep.zip</code>) and as a list of unzipped individually-accessible ROOT files containing the collision data (such as <code>data_A.4lep.root</code>) and the simulated data (such as <code>mc_301215.ZPrime2000_ee.4lep.root</code>). You can use either the tarball or the individual ROOT files.</p> <p>This dataset is provided by the ATLAS Collaboration <strong>only for educational purposes and is not suited for scientific publications</strong>.\n You can access these data through the ATLAS Virtual Machine and Software.\n More documentation is available at:</p>",
      "links": [
        {
          "description": "The ATLAS Open Data documentation for 13 TeV release",
          "url": "http://opendata.atlas.cern/release/2020/documentation/"
        },
        {
          "description": "The ATLAS Open Data site",
          "url": "http://opendata.atlas.cern/"
        }
      ]
    }
  }
]
