[
  {
    "body": {
      "content": "cms-guide-trigger-system.md",
      "format": "md"
    },
    "collections": [
      {
        "experiment": "CMS"
      },
      {
        "primary": "documentation"
      }
    ],
    "experiment": [
      "CMS"
    ],
    "short_description": {
      "content": "Physically, an event is the result of a single readout of the detector electronics and the signals that will (in general) have been generated by particles, tracks, energy deposits, present in a number of bunch crossings. The task of the online Trigger and Data Acquisition System (TriDAS) is to select,..."
    },
    "slug": "cms-guide-trigger-system",
    "tags": [
      "Getting Started"
    ],
    "title": "Guide to the CMS Trigger System",
    "type": {
      "primary": "Documentation",
      "secondary": [
        "Guide"
      ]
    }
  }
]
