[
  {
    "body": {
      "content": "cms-guide-event-production.md",
      "format": "md"
    },
    "collections": [
      {
        "experiment": "CMS"
      }
    ],
    "experiment": "CMS",
    "short_description": {
      "content": "Guide to produce CMSSW python configuration files to simulate, generate and/or reconstruct collision events."
    },
    "slug": "cms-guide-event-production",
    "tags": [
      "Getting Started"
    ],
    "title": "CMS Guide to generate configuration files for event production",
    "type": {
      "primary": "Documentation",
      "secondary": [
        "Guide"
      ]
    }
  }
]
