[
  {
    "body": {
      "content": "stripping21r0p2-bhadron-bc2dstd0dst2dgammad2kshd02khhhbeauty2charmline.md",
      "format": "md"
    },
    "date_created": [
      "2012"
    ],
    "experiment": [
      "LHCb"
    ],
    "short_description": {
      "content": " "
    },
    "slug": "stripping21r0p2-bhadron-bc2dstd0dst2dgammad2kshd02khhhbeauty2charmline",
    "stripping": {
      "stream": "BHADRON",
      "version": "stripping21r0p2"
    },
    "tags": [
      "BHADRON"
    ],
    "title": "LHCb Stripping V21r0p2 BHADRON Stream BC2DSTD0DST2DGAMMAD2KSHD02KHHHBEAUTY2CHARM Line",
    "type": {
      "primary": "Documentation",
      "secondary": [
        "Stripping"
      ]
    }
  }
]
