[
  {
    "body": {
      "content": "stripping21-bhadroncompleteevent-b2d0pipipid2hhtightbeauty2charmline.md",
      "format": "md"
    },
    "collections": [
      {
        "experiment": "LHCb"
      }
    ],
    "date_created": [
      "2012"
    ],
    "experiment": "LHCb",
    "short_description": {
      "content": " "
    },
    "slug": "stripping21-bhadroncompleteevent-b2d0pipipid2hhtightbeauty2charmline",
    "stripping": {
      "stream": "bhadroncompleteevent",
      "version": "stripping21"
    },
    "tags": [
      "BHADRONCOMPLETEEVENT"
    ],
    "title": "LHCb Stripping V21 BHADRONCOMPLETEEVENT Stream B2D0PIPIPID2HHTIGHTBEAUTY2CHARM Line",
    "type": {
      "primary": "Documentation",
      "secondary": [
        "Stripping"
      ]
    }
  }
]
