<collection xmlns="http://www.loc.gov/MARC21/slim">
  <record>
    <controlfield tag="001">FIXME TIBOR </controlfield>
    <datafield tag="024" ind1="7" ind2=" ">
      <subfield code="2">DOI</subfield>
      <subfield code="a"> FIXME </subfield>
    </datafield>
    <datafield tag="110" ind1=" " ind2=" ">
      <subfield code="a">CMS collaboration</subfield>
    </datafield>
    <datafield tag="245" ind1=" " ind2=" ">
      <subfield code="a">CMS Software Version 4_2_8 (CMSSW_4_2_8)</subfield>
    </datafield>
    <datafield tag="260" ind1=" " ind2=" ">
      <subfield code="b">CERN Open Data Portal</subfield>
      <subfield code="c">2015</subfield>
    </datafield>
    <datafield tag="264" ind1=" " ind2="0">
      <subfield code="c">2010</subfield>
    </datafield>
    <datafield tag="516" ind1=" " ind2=" ">
      <subfield code="a">Use this with primary datasets from 2010</subfield>
    </datafield>
    <datafield tag="520" ind1=" " ind2=" ">
      <subfield code="a"> CMS Software Version 4_2_8 </subfield>
    </datafield>
    <datafield tag="540" ind1=" " ind2=" ">
      <subfield code="a">Apache Lisense, Version 2.0</subfield>
    </datafield>
    <datafield tag="567" ind1=" " ind2=" ">
      <subfield code="a">SELECTION TEXT_KATI?</subfield>
    </datafield>
    <datafield tag="583" ind1=" " ind2=" ">
      <subfield code="a"> VALIDATION TEXT </subfield>
    </datafield>
    <datafield tag="693" ind1=" " ind2=" ">
      <subfield code="a">CERN-LHC</subfield>
      <subfield code="e">CMS</subfield>
    </datafield>
    <datafield tag="581" ind1=" " ind2=" ">
      <subfield code="a">See the run instructions in</subfield>
      <subfield code="u">URL</subfield>
      <subfield code="y">LINK NAMING</subfield>
    </datafield>
    <datafield tag="856" ind1="4" ind2=" ">
      <subfield code="u">FIXME TIBOR</subfield>
    </datafield>
    <datafield tag="980" ind1=" " ind2=" ">
      <subfield code="a">CMS-Tools</subfield>
    </datafield>
    <datafield tag="980" ind1=" " ind2=" ">
      <subfield code="b">Research</subfield>
    </datafield>
  </record>
</collection>
