[
  {
    "title": "CMS Pile-up simulation",
    "slug": "cms-guide-pileup-simulation",
    "short_description": {
        "content": "Monte Carlo simulation of pile-up is controlled by the code and configuration files of the CMSSW package SimGeneral/MixingModule. An input distribution is specified for each set of production samples which is supposed to represent the distribution of the mean number of interactions seen during data-taking."
    },
    "type": {"primary": "Documentation", "secondary": ["Guide"]},
    "experiment": "CMS",
    "collections": [
      {
        "experiment": "CMS"
      },
      {
        "primary": "research"
      }
    ],
    "tags":[
        "Getting Started"
    ],
    "body": {
      "content": "cms-guide-pileup-simulation.md",
      "format": "md"
    }
  }
]
